{"type": "Feature", "id": 12514879, "properties": {"woe:id": 12514879, "woe:parent_id": 115799, "woe:name": "General Francisco J Mujica Airport", "woe:placetype": 14, "woe:placetype_name": "Airport", "woe:lang": "ENG", "iso:country": "MX", "meta:provider": ["geoplanet:7.3.1", "geoplanet:7.3.2", "geoplanet:7.4.0", "geoplanet:7.4.1", "geoplanet:7.5.1", "geoplanet:7.5.2", "geoplanet:7.6.0", "geoplanet:7.8.1", "geoplanet:7.9.0", "geoplanet:7.10.0", "geoplanet:8.0.0", "woeplanet:8.0.0"], "meta:indexed": "2020-08-20T20:54:53.336742", "woe:alias_ENG_V": ["MLM Airport", "MLM"], "meta:updated": "2020-08-22T02:51:44.178125", "woe:alias_SPA_V": ["Aeropuerto Internacional de Morelia", "Aerop Intl Gral Francisco J Mujica", "Aerop Intl Gral Francisco J M\u00fajica"], "woe:hierarchy": {"continent": 24865672, "country": 23424900, "town": 0, "planet": 1, "county": 12600442, "suburb": 0, "state": 2346279, "region": 0, "localadmin": 0}, "woe:timezone_id": 56043602, "woe:hash": "9g80vh72xskf", "woe:centroid": [-101.025482, 19.842791], "geom:latitude": 19.842791, "geom:longitude": -101.025482, "geom:hash": "9g80vh72xskf", "woe:latitude": 19.842791, "geom:centroid": [-101.025482, 19.842791], "woe:longitude": -101.025482, "woe:repo": "woeplanet-airport-mx"}, "geometry": {"coordinates": [-101.025482, 19.842791], "type": "Point"}}