{"type": "Feature", "id": 12514965, "geometry": {"type": "Point", "coordinates": [-101.479828, 20.9837]}, "properties": {"woe:id": 12514965, "woe:parent_id": 117017, "woe:name": "Silao Airport", "woe:placetype": 14, "woe:placetype_name": "Airport", "woe:lang": "ENG", "iso:country": "MX", "meta:provider": ["geoplanet:7.3.1", "geoplanet:7.3.2", "geoplanet:7.4.0", "geoplanet:7.4.1", "geoplanet:7.5.1", "geoplanet:7.5.2", "geoplanet:7.6.0", "geoplanet:7.8.1", "geoplanet:7.9.0", "geoplanet:7.10.0", "geoplanet:8.0.0", "woeplanet:8.0.0"], "meta:indexed": "2020-08-20T20:54:53.359461", "woe:alias_ENG_V": ["BJX Airport", "BJX"], "meta:updated": "2020-10-14T11:24:23.788025", "woe:alias_SPA_V": ["Aeropuerto Intl de Guanajuato", "Aeropuerto Del Baj\u00edo", "Aeropuerto Del Bajio"], "woe:hierarchy": {"continent": 24865672, "country": 23424900, "town": 0, "planet": 1, "county": 12600025, "suburb": 0, "state": 2346274, "region": 0, "localadmin": 0}, "woe:timezone_id": 56043602, "woe:hash": "9exz6gbwut5y", "woe:centroid": [-101.479828, 20.9837], "geom:latitude": 20.9837, "geom:longitude": -101.479828, "geom:hash": "9exz6gbwut5y", "woe:latitude": 20.9837, "geom:centroid": [-101.479828, 20.9837], "woe:longitude": -101.479828, "woe:repo": "woeplanet-airport-mx", "geom:area": 0.0, "woe:scale": 19}}