{"type": "Feature", "id": 12514988, "properties": {"woe:id": 12514988, "woe:parent_id": 142285, "woe:name": "Zamora Airport", "woe:placetype": 14, "woe:placetype_name": "Airport", "woe:lang": "ENG", "iso:country": "MX", "meta:provider": ["geoplanet:7.3.1", "geoplanet:7.3.2", "geoplanet:7.4.0", "geoplanet:7.4.1", "geoplanet:7.5.1", "geoplanet:7.5.2", "geoplanet:7.6.0", "geoplanet:7.8.1", "geoplanet:7.9.0", "geoplanet:7.10.0", "geoplanet:8.0.0", "woeplanet:8.0.0"], "meta:indexed": "2020-08-20T20:54:53.306409", "woe:alias_ENG_V": ["ZMM Airport", "ZMM"], "meta:updated": "2020-08-22T02:51:44.161185", "woe:hierarchy": {"continent": 24865672, "country": 23424900, "town": 0, "planet": 1, "county": 12600548, "suburb": 0, "state": 2346279, "region": 0, "localadmin": 0}, "woe:timezone_id": 56043602, "woe:hash": "9ex3bt4tcvw6", "woe:centroid": [-102.279198, 20.0236], "geom:latitude": 20.0236, "geom:longitude": -102.279198, "geom:hash": "9ex3bt4tcvw6", "woe:latitude": 20.0236, "geom:centroid": [-102.279198, 20.0236], "woe:longitude": -102.279198, "woe:repo": "woeplanet-airport-mx"}, "geometry": {"coordinates": [-102.279198, 20.0236], "type": "Point"}}