{"type": "Feature", "id": 12514856, "properties": {"woe:id": 12514856, "woe:parent_id": 117780, "woe:name": "Cuatro Cienegas New Airport", "woe:placetype": 14, "woe:placetype_name": "Airport", "woe:lang": "ENG", "iso:country": "MX", "meta:provider": ["geoplanet:7.3.1", "geoplanet:7.3.2", "geoplanet:7.4.0", "geoplanet:7.4.1", "geoplanet:7.5.1", "geoplanet:7.5.2", "geoplanet:7.6.0", "geoplanet:7.8.1", "geoplanet:7.9.0", "geoplanet:7.10.0", "geoplanet:8.0.0", "woeplanet:8.0.0"], "meta:indexed": "2020-08-20T20:54:53.225392", "meta:updated": "2020-08-22T02:51:44.127802", "woe:hierarchy": {"continent": 24865672, "country": 23424900, "town": 0, "planet": 1, "county": 12599892, "suburb": 0, "state": 2346270, "region": 0, "localadmin": 0}, "woe:timezone_id": 56043601, "woe:hash": "9sz3w0ztddky", "woe:centroid": [-102.030602, 26.987499], "geom:latitude": 26.987499, "geom:longitude": -102.030602, "geom:hash": "9sz3w0ztddky", "woe:latitude": 26.987499, "geom:centroid": [-102.030602, 26.987499], "woe:longitude": -102.030602, "woe:repo": "woeplanet-airport-mx"}, "geometry": {"coordinates": [-102.030602, 26.987499], "type": "Point"}}