{"type": "Feature", "id": 12514873, "properties": {"woe:id": 12514873, "woe:parent_id": 149046, "woe:name": "Francisco Sarabia Airport", "woe:placetype": 14, "woe:placetype_name": "Airport", "woe:lang": "ENG", "iso:country": "MX", "meta:provider": ["geoplanet:7.3.1", "geoplanet:7.3.2", "geoplanet:7.4.0", "geoplanet:7.4.1", "geoplanet:7.5.1", "geoplanet:7.5.2", "geoplanet:7.6.0", "geoplanet:7.8.1", "geoplanet:7.9.0", "geoplanet:7.10.0", "geoplanet:8.0.0", "woeplanet:8.0.0"], "meta:indexed": "2020-08-20T20:54:53.332668", "meta:updated": "2020-08-22T02:51:44.175408", "woe:alias_SPA_V": ["Francisco Sarabia"], "woe:hierarchy": {"continent": 24865672, "country": 23424900, "town": 0, "planet": 1, "county": 12599809, "suburb": 0, "state": 2346268, "region": 0, "localadmin": 0}, "woe:timezone_id": 56043602, "woe:hash": "9fvxr8vhd699", "woe:centroid": [-93.17907, 16.74807], "geom:latitude": 16.74807, "geom:longitude": -93.17907, "geom:hash": "9fvxr8vhd699", "woe:latitude": 16.74807, "geom:centroid": [-93.17907, 16.74807], "woe:longitude": -93.17907, "woe:repo": "woeplanet-airport-mx"}, "geometry": {"coordinates": [-93.17907, 16.74807], "type": "Point"}}