{"type": "Feature", "id": 12514864, "properties": {"woe:id": 12514864, "woe:parent_id": 129695, "woe:name": "Durango Airport", "woe:placetype": 14, "woe:placetype_name": "Airport", "woe:lang": "ENG", "iso:country": "MX", "meta:provider": ["geoplanet:7.3.1", "geoplanet:7.3.2", "geoplanet:7.4.0", "geoplanet:7.4.1", "geoplanet:7.5.1", "geoplanet:7.5.2", "geoplanet:7.6.0", "geoplanet:7.8.1", "geoplanet:7.9.0", "geoplanet:7.10.0", "geoplanet:8.0.0", "woeplanet:8.0.0"], "meta:indexed": "2020-08-20T20:54:53.228441", "woe:alias_ENG_V": ["DGO Airport", "DGO"], "meta:updated": "2020-08-22T02:51:44.129126", "woe:hierarchy": {"continent": 24865672, "country": 23424900, "town": 0, "planet": 1, "county": 12599954, "suburb": 0, "state": 2346273, "region": 0, "localadmin": 0}, "woe:timezone_id": 56043601, "woe:hash": "9sm9m2mmsc1g", "woe:centroid": [-104.527496, 24.1283], "geom:latitude": 24.1283, "geom:longitude": -104.527496, "geom:hash": "9sm9m2mmsc1g", "woe:latitude": 24.1283, "geom:centroid": [-104.527496, 24.1283], "woe:longitude": -104.527496, "woe:repo": "woeplanet-airport-mx"}, "geometry": {"coordinates": [-104.527496, 24.1283], "type": "Point"}}