{"type": "Feature", "id": 12514950, "properties": {"woe:id": 12514950, "woe:parent_id": 116549, "woe:name": "Rio Verde Airport", "woe:placetype": 14, "woe:placetype_name": "Airport", "woe:lang": "ENG", "iso:country": "MX", "meta:provider": ["geoplanet:7.3.1", "geoplanet:7.3.2", "geoplanet:7.4.0", "geoplanet:7.4.1", "geoplanet:7.5.1", "geoplanet:7.5.2", "geoplanet:7.6.0", "geoplanet:7.8.1", "geoplanet:7.9.0", "geoplanet:7.10.0", "geoplanet:8.0.0", "woeplanet:8.0.0"], "meta:indexed": "2020-08-20T20:54:53.277630", "meta:updated": "2020-08-22T02:51:44.148719", "woe:hierarchy": {"continent": 24865672, "country": 23424900, "town": 0, "planet": 1, "county": 12601482, "suburb": 0, "state": 2346287, "region": 0, "localadmin": 0}, "woe:timezone_id": 56043602, "woe:hash": "9gbuum31qqsg", "woe:centroid": [-100.006897, 21.9578], "geom:latitude": 21.9578, "geom:longitude": -100.006897, "geom:hash": "9gbuum31qqsg", "woe:latitude": 21.9578, "geom:centroid": [-100.006897, 21.9578], "woe:longitude": -100.006897, "woe:repo": "woeplanet-airport-mx"}, "geometry": {"coordinates": [-100.006897, 21.9578], "type": "Point"}}