{"type": "Feature", "id": 12514833, "properties": {"woe:id": 12514833, "woe:parent_id": 114427, "woe:name": "Campo Gobierno Airport", "woe:placetype": 14, "woe:placetype_name": "Airport", "woe:lang": "ENG", "iso:country": "MX", "meta:provider": ["geoplanet:7.3.1", "geoplanet:7.3.2", "geoplanet:7.4.0", "geoplanet:7.4.1", "geoplanet:7.5.1", "geoplanet:7.5.2", "geoplanet:7.6.0", "geoplanet:7.8.1", "geoplanet:7.9.0", "geoplanet:7.10.0", "geoplanet:8.0.0", "woeplanet:8.0.0"], "meta:indexed": "2020-08-20T20:54:53.210581", "meta:updated": "2020-08-22T02:51:44.121306", "woe:hierarchy": {"continent": 24865672, "country": 23424900, "town": 0, "planet": 1, "county": 12601540, "suburb": 0, "state": 2346288, "region": 0, "localadmin": 0}, "woe:timezone_id": 28350774, "woe:hash": "9s7s0xg3qz27", "woe:centroid": [-107.551399, 24.652201], "geom:latitude": 24.652201, "geom:longitude": -107.551399, "geom:hash": "9s7s0xg3qz27", "woe:latitude": 24.652201, "geom:centroid": [-107.551399, 24.652201], "woe:longitude": -107.551399, "woe:repo": "woeplanet-airport-mx"}, "geometry": {"coordinates": [-107.551399, 24.652201], "type": "Point"}}