{"type": "Feature", "id": 12514825, "geometry": {"type": "Point", "coordinates": [-99.293419, 19.572281]}, "properties": {"woe:id": 12514825, "woe:parent_id": 114133, "woe:name": "Atizapan Airport", "woe:placetype": 14, "woe:placetype_name": "Airport", "woe:lang": "ENG", "iso:country": "MX", "meta:provider": ["geoplanet:7.3.1", "geoplanet:7.3.2", "geoplanet:7.4.0", "geoplanet:7.4.1", "geoplanet:7.5.1", "geoplanet:7.5.2", "geoplanet:7.6.0", "geoplanet:7.8.1", "geoplanet:7.9.0", "geoplanet:7.10.0", "geoplanet:8.0.0", "woeplanet:8.0.0"], "meta:indexed": "2020-08-20T20:54:53.320315", "woe:alias_ENG_V": ["AZP Airport", "AZP"], "meta:updated": "2020-10-14T11:24:23.818224", "woe:alias_SPA_V": ["Aeropuerto Dr Jorge Jim\u00e9nez Cant\u00fa", "Aeropuerto Dr Jorge Jimenez Cantu"], "woe:hierarchy": {"continent": 24865672, "country": 23424900, "town": 0, "planet": 1, "county": 12600330, "suburb": 0, "state": 2346278, "region": 0, "localadmin": 0}, "woe:timezone_id": 56043602, "woe:hash": "9g3rke08z9se", "woe:centroid": [-99.293419, 19.572281], "geom:latitude": 19.572281, "geom:longitude": -99.293419, "geom:hash": "9g3rke08z9se", "woe:latitude": 19.572281, "geom:centroid": [-99.293419, 19.572281], "woe:longitude": -99.293419, "woe:repo": "woeplanet-airport-mx", "geom:area": 0.0, "woe:scale": 19}}