{"type": "Feature", "id": 12514829, "properties": {"woe:id": 12514829, "woe:parent_id": 112928, "woe:name": "Bahia Tortugas Airport", "woe:placetype": 14, "woe:placetype_name": "Airport", "woe:lang": "ENG", "iso:country": "MX", "meta:provider": ["geoplanet:7.3.1", "geoplanet:7.3.2", "geoplanet:7.4.0", "geoplanet:7.4.1", "geoplanet:7.5.1", "geoplanet:7.5.2", "geoplanet:7.6.0", "geoplanet:7.8.1", "geoplanet:7.9.0", "geoplanet:7.10.0", "geoplanet:8.0.0", "woeplanet:8.0.0"], "meta:indexed": "2020-08-20T20:54:53.207601", "meta:updated": "2020-08-22T02:51:44.120028", "woe:hierarchy": {"continent": 24865672, "country": 23424900, "town": 0, "planet": 1, "county": 12599698, "suburb": 0, "state": 2346266, "region": 0, "localadmin": 0}, "woe:timezone_id": 28350774, "woe:hash": "9kym97zy1kjr", "woe:centroid": [-114.895302, 27.707199], "geom:latitude": 27.707199, "geom:longitude": -114.895302, "geom:hash": "9kym97zy1kjr", "woe:latitude": 27.707199, "geom:centroid": [-114.895302, 27.707199], "woe:longitude": -114.895302, "woe:repo": "woeplanet-airport-mx"}, "geometry": {"coordinates": [-114.895302, 27.707199], "type": "Point"}}