{"type": "Feature", "id": 12514969, "properties": {"woe:id": 12514969, "woe:parent_id": 148128, "woe:name": "Tamuin Airport", "woe:placetype": 14, "woe:placetype_name": "Airport", "woe:lang": "ENG", "iso:country": "MX", "meta:provider": ["geoplanet:7.3.1", "geoplanet:7.3.2", "geoplanet:7.4.0", "geoplanet:7.4.1", "geoplanet:7.5.1", "geoplanet:7.5.2", "geoplanet:7.6.0", "geoplanet:7.8.1", "geoplanet:7.9.0", "geoplanet:7.10.0", "geoplanet:8.0.0", "woeplanet:8.0.0"], "meta:indexed": "2020-08-20T20:54:53.293486", "woe:alias_ENG_V": ["TSL Airport", "TSL"], "meta:updated": "2020-08-22T02:51:44.155598", "woe:hierarchy": {"continent": 24865672, "country": 23424900, "town": 0, "planet": 1, "county": 12601510, "suburb": 0, "state": 2346287, "region": 0, "localadmin": 0}, "woe:timezone_id": 56043602, "woe:hash": "9gctrtkfp6c3", "woe:centroid": [-98.804199, 22.045799], "geom:latitude": 22.045799, "geom:longitude": -98.804199, "geom:hash": "9gctrtkfp6c3", "woe:latitude": 22.045799, "geom:centroid": [-98.804199, 22.045799], "woe:longitude": -98.804199, "woe:repo": "woeplanet-airport-mx"}, "geometry": {"coordinates": [-98.804199, 22.045799], "type": "Point"}}