{"type": "Feature", "id": 12514959, "properties": {"woe:id": 12514959, "woe:parent_id": 26797902, "woe:name": "San Luis Potosi Airport", "woe:placetype": 14, "woe:placetype_name": "Airport", "woe:lang": "ENG", "iso:country": "MX", "meta:provider": ["geoplanet:7.3.1", "geoplanet:7.3.2", "geoplanet:7.4.0", "geoplanet:7.4.1", "geoplanet:7.5.1", "geoplanet:7.5.2", "geoplanet:7.6.0", "geoplanet:7.8.1", "geoplanet:7.9.0", "geoplanet:7.10.0", "geoplanet:8.0.0", "woeplanet:8.0.0"], "meta:indexed": "2020-08-20T20:54:53.358782", "woe:alias_ENG_V": ["SLP Airport", "SLP"], "meta:updated": "2020-08-22T02:51:44.191975", "woe:alias_SPA_V": ["Ponciano Arriaga", "Aeropuerto Intl de San Luis Potosi", "Aeropuerto Intl de San Luis Potos\u00ed", "Aeropuerto Intl Ponciano Arriaga"], "woe:hierarchy": {"continent": 24865672, "country": 23424900, "town": 0, "planet": 1, "county": 12601498, "suburb": 0, "state": 2346287, "region": 0, "localadmin": 0}, "woe:timezone_id": 56043602, "woe:hash": "9gbnx55hqy21", "woe:centroid": [-100.937973, 22.253571], "geom:latitude": 22.253571, "geom:longitude": -100.937973, "geom:hash": "9gbnx55hqy21", "woe:latitude": 22.253571, "geom:centroid": [-100.937973, 22.253571], "woe:longitude": -100.937973, "woe:repo": "woeplanet-airport-mx"}, "geometry": {"coordinates": [-100.937973, 22.253571], "type": "Point"}}